{"errors":[],"warnings":[],"namedChunkGroups":{"app":{"chunks":[5,2],"assets":["webpack-runtime-aa2504babd5a22982239.js","webpack-runtime-aa2504babd5a22982239.js.map","app-6a46f3f496ef8cf71af4.js","app-6a46f3f496ef8cf71af4.js.map"],"children":{},"childAssets":{}},"component---src-pages-about-js":{"chunks":[0,1,3],"assets":["styles.88dcb9cfc7bbdfdbbb7b.css","styles-fc0ac7839952f78a590d.js","styles-fc0ac7839952f78a590d.js.map","1-9050c343f2a83c23b608.js","1-9050c343f2a83c23b608.js.map","component---src-pages-about-js-691d498e7ed26691bda2.js","component---src-pages-about-js-691d498e7ed26691bda2.js.map"],"children":{},"childAssets":{}},"component---src-pages-index-js":{"chunks":[0,1,4],"assets":["styles.88dcb9cfc7bbdfdbbb7b.css","styles-fc0ac7839952f78a590d.js","styles-fc0ac7839952f78a590d.js.map","1-9050c343f2a83c23b608.js","1-9050c343f2a83c23b608.js.map","component---src-pages-index-js-c1924e1de52906ddaa45.js","component---src-pages-index-js-c1924e1de52906ddaa45.js.map"],"children":{},"childAssets":{}}},"assetsByChunkName":{"app":["webpack-runtime-aa2504babd5a22982239.js","app-6a46f3f496ef8cf71af4.js"],"component---src-pages-about-js":["styles.88dcb9cfc7bbdfdbbb7b.css","styles-fc0ac7839952f78a590d.js","1-9050c343f2a83c23b608.js","component---src-pages-about-js-691d498e7ed26691bda2.js"],"component---src-pages-index-js":["styles.88dcb9cfc7bbdfdbbb7b.css","styles-fc0ac7839952f78a590d.js","1-9050c343f2a83c23b608.js","component---src-pages-index-js-c1924e1de52906ddaa45.js"]}}